auth_tg/__init__.py
auth_tg/admin.py
auth_tg/apps.py
auth_tg/authentication.py
auth_tg/forms.py
auth_tg/models.py
auth_tg/tests.py
auth_tg/tg_bot.py
auth_tg/urls.py
auth_tg/user_manager.py
auth_tg/views.py
auth_tg/management/__init__.py
auth_tg/management/commands/__init__.py
auth_tg/management/commands/start_tg_bot.py
auth_tg/migrations/__init__.py
auth_tg/static/auth_tg/js/telegramAuth.js
auth_tg/templates/admin/login.html
auth_tg/templates/auth_tg/base.html
auth_tg/templates/auth_tg/home.html
auth_tg/templates/auth_tg/profile.html
django_tgauth-0.1.4.dist-info/LICENSE
django_tgauth-0.1.4.dist-info/METADATA
django_tgauth-0.1.4.dist-info/WHEEL
django_tgauth-0.1.4.dist-info/top_level.txt
django_tgauth-0.1.4.dist-info/RECORD
