Metadata-Version: 2.2
Name: django-tgauth
Version: 0.1.4
Summary: App for Django and DRF which give an opportunity to login via TG.
Home-page: https://github.com/hraon88/tgauth
Author: hraon88
Author-email: irm7700@gmail.com
License: MIT
Classifier: Environment :: Web Environment
Classifier: Framework :: Django
Classifier: Framework :: Django :: 5.0
Classifier: Intended Audience :: Developers
Classifier: License :: OSI Approved :: MIT License
Classifier: Operating System :: OS Independent
Classifier: Programming Language :: Python
Classifier: Programming Language :: Python :: 3.12
Classifier: Topic :: Internet :: WWW/HTTP
Classifier: Topic :: Internet :: WWW/HTTP :: Dynamic Content
Requires-Python: >=3.12
License-File: LICENSE
Requires-Dist: Django<5.2,>=5.1.5
Requires-Dist: djangorestframework>=3.15.2
Requires-Dist: pyTelegramBotAPI>=4.26.0
Requires-Dist: requests>=2.25.0
Dynamic: author
Dynamic: author-email
Dynamic: classifier
Dynamic: description
Dynamic: description-content-type
Dynamic: home-page
Dynamic: license
Dynamic: requires-dist
Dynamic: requires-python
Dynamic: summary
